lakeops-0.2.0.dist-info/METADATA
lakeops-0.2.0.dist-info/WHEEL
lakeops-0.2.0.dist-info/licenses/LICENSE
lakeops/__init__.py
lakeops/_lakeops_udf.cp310-win_amd64.pyd
lakeops/core/__init__.py
lakeops/core/engines/__init__.py
lakeops/core/engines/base.py
lakeops/core/engines/duckdb.py
lakeops/core/engines/gsheet.py
lakeops/core/engines/polars.py
lakeops/core/engines/spark.py
lakeops/core/engines/spark_connect.py
lakeops/core/engines/trino.py
lakeops/core/ops.py
lakeops/core/secrets/__init__.py
lakeops/core/secrets/databricks.py
lakeops/core/secrets/interface.py
lakeops/core/secrets/sqlite.py
lakeops/core/secrets/utils.py
lakeops/udf/__init__.py
lakeops-0.2.0.dist-info/RECORD
